htmlproofer/__init__.py
htmlproofer/plugin.py
mkdocs_htmlproofer_plugin-1.3.0.dist-info/LICENSE.md
mkdocs_htmlproofer_plugin-1.3.0.dist-info/METADATA
mkdocs_htmlproofer_plugin-1.3.0.dist-info/WHEEL
mkdocs_htmlproofer_plugin-1.3.0.dist-info/entry_points.txt
mkdocs_htmlproofer_plugin-1.3.0.dist-info/top_level.txt
mkdocs_htmlproofer_plugin-1.3.0.dist-info/RECORD
