Metadata-Version: 2.1
Name: mkdocs-htmlproofer-plugin
Version: 1.3.0
Summary: A MkDocs plugin that validates URL in rendered HTML files
Home-page: https://github.com/manuzhang/mkdocs-htmlproofer-plugin
Author: Manu Zhang
Author-email: owenzhang1990@gmail.com
License: MIT
Keywords: mkdocs python markdown
Classifier: Development Status :: 5 - Production/Stable
Classifier: Intended Audience :: Developers
Classifier: Intended Audience :: Information Technology
Classifier: License :: OSI Approved :: MIT License
Classifier: Programming Language :: Python
Classifier: Programming Language :: Python :: 3 :: Only
Classifier: Programming Language :: Python :: 3.8
Classifier: Programming Language :: Python :: 3.9
Classifier: Programming Language :: Python :: 3.10
Classifier: Programming Language :: Python :: 3.11
Requires-Python: >=3.8
License-File: LICENSE.md
Requires-Dist: mkdocs (>=1.4.0)
Requires-Dist: Markdown
Requires-Dist: requests
Requires-Dist: beautifulsoup4
